{
  "packages": {
    "brotli": "latest",
    "caddy": {
      "version": "latest",
      "disable_plugin": true
    },
    "dart-sass": "latest",
    "elmPackages.elm": "latest",
    "elmPackages.elm-format": "latest",
    "elmPackages.elm-optimize-level-2": "latest",
    "elmPackages.elm-review": "latest",
    "html-minifier": "latest",
    "optipng": "latest",
    "shellcheck": "latest",
    "terser": "latest",
    "xdg-utils": "latest",
    "zopfli": "latest"
  },
  "env": {
    "project": "$PWD",
    "build": "$PWD/.build",
    "PATH": "$PWD/bin:$PATH"
  }
}
